hwrandom/__init__.py
hwrandom/librdrand.so
hwrandom/librdrand64.so
hwrandom/rdrand32.dll
hwrandom/rdrand64.dll
hwrandom-0.0.5.dist-info/LICENSE
hwrandom-0.0.5.dist-info/METADATA
hwrandom-0.0.5.dist-info/WHEEL
hwrandom-0.0.5.dist-info/top_level.txt
hwrandom-0.0.5.dist-info/RECORD
