Metadata-Version: 2.1
Name: hwrandom
Version: 0.0.5
Summary: The hwrandom Python package uses Intel’s RDRAND instruction to generate high-entropy, cryptographically secure random numbers for various applications.
Home-page: https://github.com/RaymonDev/hwrandom
Author: RaymonDev
Author-email: ramongallinadcorti@gmail.com
Keywords: random,hardware random,RDRAND,cryptographic randomness,random number generator,secure random,python
Classifier: Development Status :: 1 - Planning
Classifier: Intended Audience :: Developers
Classifier: Programming Language :: Python :: 3
Classifier: Operating System :: Unix
Classifier: Operating System :: Microsoft :: Windows
License-File: LICENSE
